{
  "stats": {
    "suites": 1,
    "tests": 8,
    "passes": 8,
    "pending": 0,
    "failures": 0,
    "start": "2021-07-31T12:53:22.546Z",
    "end": "2021-07-31T12:53:24.287Z",
    "duration": 1682,
    "testsRegistered": 8,
    "passPercent": 100,
    "pendingPercent": 0,
    "other": 0,
    "hasOther": false,
    "skipped": 0,
    "hasSkipped": false
  },
  "results": [
    {
      "uuid": "a61b0ac6-a01f-4c3e-bc0d-e3748729adc4",
      "title": "",
      "fullFile": "cypress/integration/promiseFunction.spec.js",
      "file": "cypress/integration/promiseFunction.spec.js",
      "beforeHooks": [],
      "afterHooks": [],
      "tests": [],
      "suites": [
        {
          "uuid": "b26108c6-7490-4ce4-b78b-2187f9a457a6",
          "title": "Promise function app",
          "fullFile": "",
          "file": "",
          "beforeHooks": [],
          "afterHooks": [],
          "tests": [
            {
              "title": "should resolve 'click' promise for 'login' field",
              "fullTitle": "Promise function app should resolve 'click' promise for 'login' field",
              "timedOut": null,
              "duration": 284,
              "state": "passed",
              "speed": "slow",
              "pass": true,
              "fail": false,
              "pending": false,
              "context": null,
              "code": "cy.get('#login').click();\ncy.checkNotificationExists('click', 'INPUT', 'login');",
              "err": {},
              "uuid": "8e7bd17c-d0e0-4698-a985-f87efd755423",
              "parentUUID": "b26108c6-7490-4ce4-b78b-2187f9a457a6",
              "isHook": false,
              "skipped": false
            },
            {
              "title": "should resolve 'input' promise for 'login' field",
              "fullTitle": "Promise function app should resolve 'input' promise for 'login' field",
              "timedOut": null,
              "duration": 283,
              "state": "passed",
              "speed": "slow",
              "pass": true,
              "fail": false,
              "pending": false,
              "context": null,
              "code": "cy.get('#login').type('login');\ncy.checkNotificationExists('input', 'INPUT', 'login');",
              "err": {},
              "uuid": "814ac664-3614-4128-a7ca-20a093f53356",
              "parentUUID": "b26108c6-7490-4ce4-b78b-2187f9a457a6",
              "isHook": false,
              "skipped": false
            },
            {
              "title": "should resolve 'blur' promise for 'login' field",
              "fullTitle": "Promise function app should resolve 'blur' promise for 'login' field",
              "timedOut": null,
              "duration": 200,
              "state": "passed",
              "speed": "slow",
              "pass": true,
              "fail": false,
              "pending": false,
              "context": null,
              "code": "cy.get('#login').click().blur();\ncy.checkNotificationExists('blur', 'INPUT', 'login');",
              "err": {},
              "uuid": "c5425245-196c-40ef-8aa7-bc2adb5c288a",
              "parentUUID": "b26108c6-7490-4ce4-b78b-2187f9a457a6",
              "isHook": false,
              "skipped": false
            },
            {
              "title": "should resolve 'click' promise for 'password' field",
              "fullTitle": "Promise function app should resolve 'click' promise for 'password' field",
              "timedOut": null,
              "duration": 158,
              "state": "passed",
              "speed": "slow",
              "pass": true,
              "fail": false,
              "pending": false,
              "context": null,
              "code": "cy.get('#password').click();\ncy.checkNotificationExists('click', 'INPUT', 'password');",
              "err": {},
              "uuid": "84eea5e5-c396-4915-aabc-3bf3d5259e30",
              "parentUUID": "b26108c6-7490-4ce4-b78b-2187f9a457a6",
              "isHook": false,
              "skipped": false
            },
            {
              "title": "should resolve 'input' promise for 'password' field",
              "fullTitle": "Promise function app should resolve 'input' promise for 'password' field",
              "timedOut": null,
              "duration": 273,
              "state": "passed",
              "speed": "slow",
              "pass": true,
              "fail": false,
              "pending": false,
              "context": null,
              "code": "cy.get('#password').type('login');\ncy.checkNotificationExists('input', 'INPUT', 'password');",
              "err": {},
              "uuid": "a66a362a-251e-4446-9911-6580057b88b8",
              "parentUUID": "b26108c6-7490-4ce4-b78b-2187f9a457a6",
              "isHook": false,
              "skipped": false
            },
            {
              "title": "should resolve 'blur' promise for 'password' field",
              "fullTitle": "Promise function app should resolve 'blur' promise for 'password' field",
              "timedOut": null,
              "duration": 174,
              "state": "passed",
              "speed": "slow",
              "pass": true,
              "fail": false,
              "pending": false,
              "context": null,
              "code": "cy.get('#password').click().blur();\ncy.checkNotificationExists('blur', 'INPUT', 'password');",
              "err": {},
              "uuid": "a1315e2d-5cb6-4486-a01c-739f9a159ab5",
              "parentUUID": "b26108c6-7490-4ce4-b78b-2187f9a457a6",
              "isHook": false,
              "skipped": false
            },
            {
              "title": "should resolve 'click' promise for 'submit' button",
              "fullTitle": "Promise function app should resolve 'click' promise for 'submit' button",
              "timedOut": null,
              "duration": 139,
              "state": "passed",
              "speed": "slow",
              "pass": true,
              "fail": false,
              "pending": false,
              "context": null,
              "code": "cy.get('#submit').click();\ncy.checkNotificationExists('click', 'BUTTON', 'submit');",
              "err": {},
              "uuid": "08568004-a116-4ac8-ab34-eb2b44a11888",
              "parentUUID": "b26108c6-7490-4ce4-b78b-2187f9a457a6",
              "isHook": false,
              "skipped": false
            },
            {
              "title": "should resolve 'blur' promise for 'submit' button",
              "fullTitle": "Promise function app should resolve 'blur' promise for 'submit' button",
              "timedOut": null,
              "duration": 171,
              "state": "passed",
              "speed": "slow",
              "pass": true,
              "fail": false,
              "pending": false,
              "context": null,
              "code": "cy.get('#submit').click().blur();\ncy.checkNotificationExists('blur', 'BUTTON', 'submit');",
              "err": {},
              "uuid": "6d84fedf-e512-46c9-887d-1e11b408e8dd",
              "parentUUID": "b26108c6-7490-4ce4-b78b-2187f9a457a6",
              "isHook": false,
              "skipped": false
            }
          ],
          "suites": [],
          "passes": [
            "8e7bd17c-d0e0-4698-a985-f87efd755423",
            "814ac664-3614-4128-a7ca-20a093f53356",
            "c5425245-196c-40ef-8aa7-bc2adb5c288a",
            "84eea5e5-c396-4915-aabc-3bf3d5259e30",
            "a66a362a-251e-4446-9911-6580057b88b8",
            "a1315e2d-5cb6-4486-a01c-739f9a159ab5",
            "08568004-a116-4ac8-ab34-eb2b44a11888",
            "6d84fedf-e512-46c9-887d-1e11b408e8dd"
          ],
          "failures": [],
          "pending": [],
          "skipped": [],
          "duration": 1682,
          "root": false,
          "rootEmpty": false,
          "_timeout": 2000
        }
      ],
      "passes": [],
      "failures": [],
      "pending": [],
      "skipped": [],
      "duration": 0,
      "root": true,
      "rootEmpty": true,
      "_timeout": 2000
    }
  ],
  "meta": {
    "mocha": {
      "version": "7.0.1"
    },
    "mochawesome": {
      "options": {
        "quiet": false,
        "reportFilename": "mochawesome",
        "saveHtml": false,
        "saveJson": true,
        "consoleReporter": "spec",
        "useInlineDiffs": false,
        "code": true
      },
      "version": "6.2.1"
    },
    "marge": {
      "options": {
        "reportDir": "raw_reports",
        "overwrite": false,
        "html": false,
        "json": true
      },
      "version": "5.1.0"
    }
  }
}